{"$schema":"http://schema.management.azure.com/schemas/2015-01-01/deploymentTemplate.json#","contentVersion":"1.0.0.0","parameters":{"https://dataartisans7-my.sharepoint.com/personal/jaswanth_dataartisans_net/ jasw":{"type":"string"},"lh_MountStreet":{"type":"string"}},"variables":{},"resources":[{"name":"Orc","type":"pipelines","apiVersion":"2018-06-01","properties":{"activities":[{"name":"ms_api-lh","type":"Copy","state":"Inactive","onInactiveMarkAs":"Succeeded","dependsOn":[],"policy":{"timeout":"0.12:00:00","retry":0,"retryIntervalInSeconds":30,"secureOutput":false,"secureInput":false},"typeProperties":{"source":{"type":"RestSource","httpRequestTimeout":"00:01:40","requestInterval":"00.00:00:00.010","requestMethod":"GET","paginationRules":{"supportRFC5988":"true"},"datasetSettings":{"annotations":[],"type":"RestResource","typeProperties":{},"schema":[],"externalReferences":{"connection":"[parameters('https://dataartisans7-my.sharepoint.com/personal/jaswanth_dataartisans_net/ jasw')]"}}},"sink":{"type":"BinarySink","storeSettings":{"type":"AzureBlobStorageWriteSettings"},"datasetSettings":{"annotations":[],"linkedService":{"name":"lh_MountStreet","properties":{"annotations":[],"type":"Lakehouse","typeProperties":{"workspaceId":"9dccbb8f-a671-47ac-a776-571303a66a01","artifactId":"[parameters('lh_MountStreet')]","rootFolder":"Files"}}},"type":"Binary","typeProperties":{"location":{"type":"LakehouseLocation"}}}},"enableStaging":false,"translator":{"type":"TabularTranslator","typeConversion":true,"typeConversionSettings":{"allowDataTruncation":true,"treatBooleanAsNumber":false},"columnFlattenSettings":{"treatArrayAsString":false,"treatStructAsString":false,"flattenColumnDelimiter":"."}}}},{"name":"Notebook1","type":"TridentNotebook","dependsOn":[{"activity":"ms_api-lh","dependencyConditions":["Succeeded"]}],"policy":{"timeout":"0.12:00:00","retry":0,"retryIntervalInSeconds":30,"secureOutput":false,"secureInput":false},"typeProperties":{"notebookId":"2207f896-f2f2-4626-b304-4aa6dc0849e4","workspaceId":"9dccbb8f-a671-47ac-a776-571303a66a01"}}],"lastModifiedByObjectId":"2c65a667-8d3a-472a-94c9-7f6d13a23851","lastPublishTime":"2026-03-26T13:01:46Z"},"dependsOn":[]}]}